libmozevent/__init__.py
libmozevent/bus.py
libmozevent/monitoring.py
libmozevent/phabricator.py
libmozevent/pulse.py
libmozevent/storage.py
libmozevent/utils.py
libmozevent/web.py
libmozevent-1.1.34.dist-info/LICENSE
libmozevent-1.1.34.dist-info/METADATA
libmozevent-1.1.34.dist-info/WHEEL
libmozevent-1.1.34.dist-info/top_level.txt
libmozevent-1.1.34.dist-info/RECORD
