Metadata-Version: 2.1
Name: libmozevent
Version: 1.1.34
Summary: Listens to Mozilla event sources and build workflows on top.
Home-page: https://github.com/mozilla/libmozevent
Author: Mozilla Release Management
Author-email: release-mgmt-analysis@mozilla.com
License: MPL2
Platform: UNKNOWN
Requires-Dist: aioamqp (>=0.13.0)
Requires-Dist: aiohttp
Requires-Dist: libmozdata
Requires-Dist: pytoml
Requires-Dist: redis
Requires-Dist: requests
Requires-Dist: rs-parsepatch
Requires-Dist: structlog
Requires-Dist: taskcluster (>=24.0.0)
